LICENSE
mettmail/__init__.py
mettmail/config_schema.py
mettmail/deliver_base.py
mettmail/deliver_lmtp.py
mettmail/exceptions.py
mettmail/fetch_imap.py
mettmail/mettmail_cli.py
mettmail/mettmail_loop.py
mettmail-0.1.1.dist-info/entry_points.txt
mettmail-0.1.1.dist-info/LICENSE
mettmail-0.1.1.dist-info/WHEEL
mettmail-0.1.1.dist-info/METADATA
mettmail-0.1.1.dist-info/RECORD
