Metadata-Version: 2.1
Name: mettmail
Version: 0.1.1
Summary: Fetch mails from IMAP servers and deliver them to a local user
Home-page: https://github.com/spezifisch/mettmail
License: GPL-3.0-only
Keywords: mail,email,imap,lmtp
Author: spezifisch
Author-email: spezifisch-gpl.7e6@below.fr
Requires-Python: >=3.8.0,<4.0.0
Classifier: Development Status :: 3 - Alpha
Classifier: Environment :: Console
Classifier: Framework :: Pytest
Classifier: License :: OSI Approved :: GNU General Public License v3 (GPLv3)
Classifier: Operating System :: OS Independent
Classifier: Programming Language :: Python :: 3
Classifier: Programming Language :: Python :: 3.10
Classifier: Programming Language :: Python :: 3.8
Classifier: Programming Language :: Python :: 3.9
Classifier: Topic :: Communications :: Email
Classifier: Topic :: System :: Archiving :: Mirroring
Requires-Dist: aioimaplib (>=0.9.0,<0.10.0)
Requires-Dist: click (>=8.0.3,<9.0.0)
Requires-Dist: loguru (>=0.5.3,<0.6.0)
Requires-Dist: strictyaml (>=1.6.1,<2.0.0)
Project-URL: Repository, https://github.com/spezifisch/mettmail
